{
  "items": [
    {
      "name": "10-regular-expression-matching.py"
    },
    {
      "name": "1049-last-stone-weight-ii.py"
    },
    {
      "name": "1092-shortest-common-supersequence.py"
    },
    {
      "name": "1105-filling-bookcase-shelves.py"
    },
    {
      "name": "1143-longest-common-subsequence.py"
    },
    {
      "name": "115-distinct-subsequences.py"
    },
    {
      "name": "123-best-time-to-buy-and-sell-stock-iii.py"
    },
    {
      "name": "1278-palindrome-partitioning-iii.py"
    },
    {
      "name": "1335-minimum-difficulty-of-a-job-schedule.py"
    },
    {
      "name": "139-word-break.java"
    },
    {
      "name": "139-word-break.py"
    },
    {
      "name": "152-maximum-product-subarray.py"
    },
    {
      "name": "1547-minimum-cost-to-cut-a-stick.py"
    },
    {
      "name": "1964-find-the-longest-valid-obstacle-course-at-each-position.py"
    },
    {
      "name": "198-house-robber.java"
    },
    {
      "name": "198-house-robber.py"
    },
    {
      "name": "213-house-robber-ii.py"
    },
    {
      "name": "221-maximal-square.py"
    },
    {
      "name": "256-paint-house.py"
    },
    {
      "name": "279-perfect-squares.py"
    },
    {
      "name": "300-longest-increasing-subsequence.py"
    },
    {
      "name": "309-best-time-to-buy-and-sell-stock-with-cooldown.py"
    },
    {
      "name": "312-burst-balloons.py"
    },
    {
      "name": "322-coin-change.java"
    },
    {
      "name": "322-coin-change.py"
    },
    {
      "name": "354-russian-doll-envelopes.py"
    },
    {
      "name": "368-largest-divisible-subset.py"
    },
    {
      "name": "376-wiggle-subsequence.py"
    },
    {
      "name": "377-combination-sum-iv.py"
    },
    {
      "name": "410-split-array-largest-sum.py"
    },
    {
      "name": "416-partition-equal-subset-sum.java"
    },
    {
      "name": "416-partition-equal-subset-sum.py"
    },
    {
      "name": "474-ones-and-zeroes.py"
    },
    {
      "name": "487-max-consecutive-ones-ii.py"
    },
    {
      "name": "494-target-sum.py"
    },
    {
      "name": "516-longest-palindromic-subsequence.py"
    },
    {
      "name": "518-coin-change-ii.py"
    },
    {
      "name": "55-jump-game.py"
    },
    {
      "name": "62-unique-paths.java"
    },
    {
      "name": "62-unique-paths.py"
    },
    {
      "name": "63-unique-paths-ii.py"
    },
    {
      "name": "64-minimum-path-sum.py"
    },
    {
      "name": "647-palindromic-substrings.py"
    },
    {
      "name": "688-knight-probability-in-chessboard.py"
    },
    {
      "name": "70-climbing-stairs.java"
    },
    {
      "name": "70-climbing-stairs.py"
    },
    {
      "name": "72-edit-distance.py"
    },
    {
      "name": "91-decode-ways.py"
    },
    {
      "name": "97-interleaving-string.py"
    }
  ]
}
